{
    "Kingdom": "Animalia",
    "Phylum": "Chordata",
    "Class": "Reptilia",
    "Order": "Testudines",
    "Family": "Testudinidae",
    "Genus": "Geochelone",
    "Scientific Name": "Geochelone gigantea",
    "Prey": "Grasses, Leaves, Flowers",
    "Name Of Young": "Hatchling",
    "Group Behavior": "Herd",
    "Fun Fact": "One got to be 255 years old!",
    "Estimated Population Size": "200,000",
    "Biggest Threat": "Habitat loss",
    "Most Distinctive Feature": "Large, high-domed shell",
    "Other Name(s)": "Giant Tortoise",
    "Incubation Period": "8 months",
    "Age Of Independence": "3 - 6 months",
    "Habitat": "Grasslands and swamps",
    "Predators": "Giant Crab, Humans, Cats",
    "Diet": "Herbivore",
    "Lifestyle": "Diurnal",
    "Common Name": "Aldabra Giant Tortoise",
    "Number Of Species": "1",
    "Location": "Aldabra atoll in the Indian Ocean",
    "Average Clutch Size": "15",
    "Slogan": "One got to be 255 years old!",
    "Group": "Reptile",
    "Colour": "BrownBlackTan",
    "Skin Type": "Scales",
    "Top Speed": "0.3 mph",
    "Lifespan": "80 - 255 years",
    "Weight": "150kg - 250kg (330lbs - 550lbs)",
    "Length": "90cm - 120cm (3ft - 4ft)",
    "Age of Sexual Maturity": "20 - 30 years",
    "Name": "Aldabra Giant Tortoise",
    "Status": "Vulnerable",
    "locations": [
        "Ocean"
    ]
}