{
    "Kingdom": "Animalia",
    "Phylum": "Chordata",
    "Class": "Mammalia",
    "Order": "Rodentia",
    "Family": "Sciuridae",
    "Genus": "Pteromyini",
    "Scientific Name": "Pteromyini",
    "Main Prey": "Nuts, Berries, Eggs",
    "Distinctive Feature": "Small body size and furry glide membrane",
    "Habitat": "Forest and woodland",
    "Predators": "Cats. Coyote, Raccoon",
    "Diet": "Omnivore",
    "Average Litter Size": "4",
    "Lifestyle": "Solitary",
    "Favorite Food": "Nuts",
    "Type": "Mammal",
    "Slogan": "Can glide up to 90 meters!",
    "Colour": "BrownGreyBlackWhiteTan",
    "Skin Type": "Fur",
    "Top Speed": "15 mph",
    "Lifespan": "5 - 8 years",
    "Weight": "56g - 175g (2oz - 6oz)",
    "Height": "20cm - 30cm (8in - 12in)",
    "Name": "Flying Squirrel",
    "Status": "Least Concern",
    "locations": [
        "Asia",
        "Central-America",
        "Eurasia",
        "Europe",
        "North-America",
        "South-America"
    ]
}