{
    "Kingdom": "Animalia",
    "Phylum": "Chordata",
    "Class": "Mammalia",
    "Order": "Artiodactyla",
    "Family": "Phocoenidae",
    "Genus": "Phocoena",
    "Scientific Name": "Phocoena sinus",
    "Prey": "Fish, crustaceans, squid",
    "Main Prey": "Sharks",
    "Group Behavior": "School",
    "Fun Fact": "Smallest cetacean in the ocean",
    "Estimated Population Size": "10",
    "Biggest Threat": "By-catch",
    "Most Distinctive Feature": "No beak, dark rings around eyes",
    "Other Name(s)": "Little cow",
    "Gestation Period": "11 months",
    "Water Type": "Salt",
    "Habitat": "Ocean",
    "Predators": "Sharks",
    "Diet": "Omnivore",
    "Type": "Cetacean",
    "Common Name": "Vaquita",
    "Colour": "Grey",
    "Skin Type": "Skin",
    "Lifespan": "240",
    "Weight": "90 lbs",
    "Length": "4-5 feet",
    "Name": "Vaquita",
    "Status": "Critically Endangered",
    "locations": [
        "North-America",
        "Ocean"
    ]
}