{
    "Kingdom": "Animalia",
    "Phylum": "Chordata",
    "Class": "Amphibia",
    "Order": "Anura",
    "Family": "Pyxicephalidae",
    "Genus": "Pyxicephalus",
    "Scientific Name": "Pyxicephalus adspersus",
    "Main Prey": "Reptiles, small mammals, small birds, insects, amphibians, including other frogs",
    "Name Of Young": "Tadpole, polliwog, larva",
    "Group Behavior": "Solitary",
    "Fun Fact": "The African bullfrog is one of only three species of frog that have “teeth.”",
    "Estimated Population Size": "Unknown",
    "Biggest Threat": "Habitat destruction, hunting, pet trade",
    "Most Distinctive Feature": "Size",
    "Other Name(s)": "Pixie frog, Giant African Bullfrog",
    "Water Type": "Fresh",
    "Litter Size": "As many as 4000 eggs laid at a time",
    "Habitat": "Deserts, high veld, floodplains, grassland, savanna, farms, marshes, ponds, lakes",
    "Predators": "Humans",
    "Diet": "Carnivore",
    "Type": "Amphibian",
    "Common Name": "African bullfrog",
    "Number Of Species": "1",
    "Location": "Sub-Saharan Africa",
    "Colour": "YellowCreamOliveLight-Brown",
    "Skin Type": "Permeable",
    "Lifespan": "45 years",
    "Weight": "0.9 to 18 kilograms (2 - 4 pounds)",
    "Length": "11.43 - 25.4 centimeters (4.5 - 10 inches)",
    "Age of Sexual Maturity": "1.5 - 2 years",
    "Name": "African Bullfrog",
    "Status": "Least Concern",
    "locations": [
        "Africa"
    ]
}