{
    "Kingdom": "Animalia",
    "Phylum": "Chordata",
    "Class": "Actinopterygii",
    "Order": "Scorpaeniformes",
    "Family": "Scorpaenidae",
    "Scientific Name": "Scorpaenidae",
    "Prey": "Coral reef, snails, and small fishes",
    "Group Behavior": "Solitary",
    "Fun Fact": "These fishes have venom covered spines all over their bodies.",
    "Estimated Population Size": "Not known",
    "Biggest Threat": "Sharks, rays, and large snappers",
    "Most Distinctive Feature": "Venom mucous covered sharp spines",
    "Gestation Period": "3 to 18 months",
    "Water Type": "Salt",
    "Optimum pH Level": "8.1 - 8.4",
    "Habitat": "Indian Ocean, Pacific Ocean, and Indonesia",
    "Predators": "Sharks, snappers, and rays",
    "Diet": "Omnivore",
    "Favorite Food": "Coral reefs, small fishes, snails",
    "Type": "Fish",
    "Common Name": "Scorpionfish",
    "Number Of Species": "198",
    "Average Clutch Size": "6000",
    "Slogan": "There are more than 200 recognised species!",
    "Colour": "BrownYellowRedOrange",
    "Skin Type": "Scales",
    "Lifespan": "15 years",
    "Weight": "3.4 pounds",
    "Length": "8 inches to 20 inches",
    "Name": "Scorpion Fish",
    "Status": "Not Evaluated",
    "locations": [
        "Ocean"
    ]
}