{
    "Kingdom": "Animalia",
    "Phylum": "Chordata",
    "Class": "Mammalia",
    "Order": "Carnivora",
    "Family": "Canidae",
    "Genus": "Canis",
    "Scientific Name": "Canis lupus occidentalis",
    "Prey": "Rodents, moose, bison, elk, caribou, sheep, mountain goats, deer, beavers, salmon, rabbits, squirrels, vole, and lemmings.",
    "Name Of Young": "pup",
    "Group Behavior": "Pack",
    "Fun Fact": "Will travel up to 70 miles in a single day.",
    "Estimated Population Size": "40,000+",
    "Biggest Threat": "Grizzly bears, polar bears, tigers, scavengers, and humans.",
    "Most Distinctive Feature": "gray coat",
    "Other Name(s)": "Northwestern wolf, Mackenzie Valley wolf, Rocky Mountain wolf, Alaskan timber wolf, or Canadian timber wolf.",
    "Gestation Period": "Approximately 63 days",
    "Litter Size": "4-6 pups",
    "Habitat": "Mountains, forests.",
    "Predators": "Grizzly bears, polar bears, tigers, scavengers, and humans.",
    "Diet": "Carnivore",
    "Type": "Mammal",
    "Common Name": "Northwestern wolf",
    "Number Of Species": "1",
    "Location": "Western North America",
    "Colour": "GreyWhite",
    "Skin Type": "Fur",
    "Top Speed": "40 mph",
    "Lifespan": "6-8 years, though some can live up to 17 years in captivity",
    "Weight": "85-153 lbs",
    "Height": "32-40 inches tall",
    "Age of Sexual Maturity": "2 years for females, 3 years for males.",
    "Age of Weaning": "8 weeks",
    "Name": "Mackenzie Wolf",
    "Status": "Endangered",
    "locations": [
        "North-America"
    ]
}