{
    "Kingdom": "Animalia",
    "Phylum": "Chordata",
    "Class": "Mammalia",
    "Order": "Chiroptera",
    "Family": "Molossidae",
    "Genus": "Tadarida",
    "Scientific Name": "Tadarida brasiliensis",
    "Prey": "Moths",
    "Name Of Young": "Pup",
    "Group Behavior": "Social",
    "Fun Fact": "Some colonies have millions of bats",
    "Estimated Population Size": "120 to 150 million",
    "Biggest Threat": "Mining in caves",
    "Most Distinctive Feature": "Large, rounded ears",
    "Other Name(s)": "Guano bats, Brazilian free-tailed bats, mastiff bats",
    "Gestation Period": "11-12 weeks",
    "Litter Size": "1",
    "Habitat": "Caves, tunnels, under bridges",
    "Diet": "Carnivore",
    "Type": "Mammal",
    "Common Name": "Mexican free-tailed bat",
    "Number Of Species": "9",
    "Location": "Southern United States, Mexico, northern parts of South America",
    "Colour": "GreyBlackDark Brown",
    "Skin Type": "Fur",
    "Top Speed": "47 mph",
    "Lifespan": "18 years",
    "Age of Sexual Maturity": "2 years",
    "Age of Weaning": "6 weeks",
    "Name": "Mexican Free-Tailed Bat",
    "Status": "Least Concern",
    "locations": [
        "Central-America",
        "North-America",
        "South-America"
    ]
}